aws_ou_membership/__about__.py
aws_ou_membership/__init__.py
aws_ou_membership/checker.py
aws_ou_membership/client.py
aws_ou_membership-0.1.0.dist-info/METADATA
aws_ou_membership-0.1.0.dist-info/WHEEL
aws_ou_membership-0.1.0.dist-info/licenses/LICENSE.txt
aws_ou_membership-0.1.0.dist-info/RECORD
